cloudiq/__init__.py
cloudiq/cloudiq.py
crayon_cloudiq_sdk-1.0.0.dist-info/LICENSE
crayon_cloudiq_sdk-1.0.0.dist-info/METADATA
crayon_cloudiq_sdk-1.0.0.dist-info/WHEEL
crayon_cloudiq_sdk-1.0.0.dist-info/top_level.txt
crayon_cloudiq_sdk-1.0.0.dist-info/RECORD
