Metadata-Version: 2.1
Name: crayon-cloudiq-sdk
Version: 1.0.0
Summary: SDK for Crayon's Cloud-IQ API
Author-email: Joe Courtney <jccourtn@gmail.com>
Project-URL: Homepage, https://github.com/blastomussa/crayon-python-sdk
Project-URL: Bug Tracker, https://github.com/blastomussa/crayon-python-sdk/issues
Classifier: Programming Language :: Python :: 3
Classifier: License :: OSI Approved :: MIT License
Classifier: Operating System :: OS Independent
Requires-Python: >=3.7
License-File: LICENSE
Requires-Dist: requests (>=2.0)
